{
  "name": "coding-assistant",
  "version": "1.0.0",
  "description": "AI-powered coding assistant for code generation, debugging, and refactoring.",
  "author": "Hermes Agent",
  "license": "MIT",
  "platforms": [
    "linux",
    "macos"
  ],
  "commands": [],
  "tags": "AI, Coding, Assistant, Automation",
  "hermes": {
    "skill_category": "general",
    "compatibility": [
      "hermes-agent >= 1.0.0"
    ]
  },
  "files": [
    "SKILL.md"
  ],
  "last_updated": "2026-06-05",
  "status": "stable"
}
