{
  "name": "specialized-risk-assessor",
  "version": "1.0.0",
  "description": "面向中国企业的全面风险管理专家，精通国企风控体系建设、内控合规（COSO 框架本土化）、审计整改、ESG 风险管理及供应链风险评估，帮助企业构建系统化的风险识别、评估与应对机制，提升组织韧性。",
  "author": "agency-agents-zh",
  "license": "MIT",
  "platforms": [
    "linux",
    "macos"
  ],
  "commands": [],
  "tags": "[specialized]",
  "hermes": {
    "skill_category": "specialized",
    "compatibility": [
      "hermes-agent >= 1.0.0"
    ]
  },
  "files": [
    "SKILL.md"
  ],
  "last_updated": "2026-05-03",
  "status": "stable"
}
